parsedan/CLI_Handler.py
parsedan/Nist.py
parsedan/ShodanParser.py
parsedan/Utility.py
parsedan/__init__.py
parsedan/__main__.py
parsedan/db/SQLDBHandler.py
parsedan/db/__init__.py
parsedan/db/sqlmodels.py
parsedan-0.1.1b2.dist-info/LICENSE.txt
parsedan-0.1.1b2.dist-info/METADATA
parsedan-0.1.1b2.dist-info/WHEEL
parsedan-0.1.1b2.dist-info/entry_points.txt
parsedan-0.1.1b2.dist-info/top_level.txt
parsedan-0.1.1b2.dist-info/RECORD
