Metadata-Version: 2.1
Name: parsedan
Version: 0.1.1b2
Summary: A shodan parser that given a query will download results and parse them into CSV or JSON files while also scoring them.
Home-page: https://github.com/SDMI-Developers/parsedan
Author: Louisiana State University at Stephenson Disaster Management Institute
Author-email: sdmidev@lsu.edu
License: MIT
Platform: UNKNOWN
Requires-Dist: click (~=8.0.3)
Requires-Dist: netaddr (==0.8.*)
Requires-Dist: python-dateutil (==2.8.*)
Requires-Dist: shodan (~=1.25.0)
Requires-Dist: sqlalchemy (==1.4.*)
